flowtool/__init__.py
flowtool/_version.py
flowtool/execute.py
flowtool/files.py
flowtool/info.py
flowtool/main.py
flowtool/python.py
flowtool/style.py
flowtool/ui.py
flowtool/update.py
flowtool_base-0.7.61.data/data/README
flowtool_base-0.7.61.dist-info/DESCRIPTION.rst
flowtool_base-0.7.61.dist-info/METADATA
flowtool_base-0.7.61.dist-info/RECORD
flowtool_base-0.7.61.dist-info/WHEEL
flowtool_base-0.7.61.dist-info/entry_points.txt
flowtool_base-0.7.61.dist-info/metadata.json
flowtool_base-0.7.61.dist-info/top_level.txt
tests/__init__.py
tests/setup_command.py
tests/test_execute.py
tests/test_files.py
tests/test_info.py
tests/test_main.py
tests/test_python.py
tests/test_style.py
tests/test_ui.py
tests/test_update.py
