Metadata-Version: 2.0
Name: flowtool-base
Version: 0.7.61
Summary: Start managing your workflow!
Home-page: https://github.com/isnok/py-flowlib
Author: Konstantin Martini
Author-email: k@tuxcode.org
License: UNKNOWN
Keywords: git,flow,commandline,development
Platform: Debian/GNU Linux
Classifier: Development Status :: 3 - Alpha
Classifier: Programming Language :: Python
Classifier: Programming Language :: Python :: 2.7
Classifier: Programming Language :: Python :: 3.3
Classifier: Programming Language :: Python :: 3.4
Classifier: Programming Language :: Python :: 3.5
Classifier: Topic :: System :: Software Distribution
Classifier: Topic :: System :: Systems Administration
Classifier: Topic :: Utilities
Classifier: Intended Audience :: Developers
Classifier: Intended Audience :: System Administrators
Classifier: Operating System :: POSIX
Classifier: Operating System :: Unix
Classifier: Environment :: Console
Requires-Dist: click (>=4.0)
Requires-Dist: colorama (>=0.3.0)
Requires-Dist: pip (>=6.0)
